gru/__init__.py
gru/client.py
gru/conf.py
gru/auth/__init__.py
gru/auth/generate_access_token.py
gru/cookiecutter/__init__.py
gru/cookiecutter/mlops_templates_cli.py
gru/features/__init__.py
gru/features/aggregations.py
gru/features/custom_feature_logic.py
gru/features/derived_feature.py
gru/features/feature_logic.py
gru/features/ml_feature.py
gru/features/online_feature_store.py
gru/features/processing_engine_configs.py
gru/features/raw_feature.py
gru/features/streaming_feature.py
gru/features/update_feature.py
gru/infra/__init__.py
gru/infra/deploy_infrastructure.py
gru/infra/infrastructure.py
gru/ml_serving/__init__.py
gru/ml_serving/ml_serving_config_reader.py
gru/ml_serving/request_handler.py
gru/ml_serving/response_handler.py
gru/ml_serving/server.py
gru/ml_serving/servers/__init__.py
gru/ml_serving/servers/gunicorn.py
gru/ml_serving/servers/ml_server_interface.py
gru/ml_serving/web_frameworks/__init__.py
gru/ml_serving/web_frameworks/flask_adapter.py
gru/ml_serving/web_frameworks/web_framework_adapter.py
gru/ml_training/__init__.py
gru/ml_training/generate_training_data.py
gru/preprocess/__init__.py
gru/preprocess/preprocessing_transform.py
gru/preprocess/update_preprocessing_transform.py
gru/redis_helpers/__init__.py
gru/redis_helpers/elasticache.py
gru/registry/__init__.py
gru/registry/registry.py
gru/sinks/__init__.py
gru/sinks/mysqldb.py
gru/sinks/object_storage.py
gru/sinks/redis.py
gru/sinks/sink.py
gru/sinks/sink_family.py
gru/sources/__init__.py
gru/sources/datasource.py
gru/sources/file_types.py
gru/sources/kafka_data_source.py
gru/sources/s3_data_source.py
gru/tests/__init__.py
gru/tests/test_aggregations.py
gru/tests/test_processing_engine.py
gru/tests/test_processing_engine_configs.py
gru/tests/test_raw_feature.py
gru/tests/test_streaming_feature.py
gru/utils/__init__.py
gru/utils/cloud_providers.py
gru/utils/commons.py
gru/utils/config_reader.py
gru/utils/data_processing_paradigms.py
gru/utils/data_types.py
gru/utils/deployment_workflow.py
gru-0.0.1.dist-info/LICENSE
gru-0.0.1.dist-info/METADATA
gru-0.0.1.dist-info/WHEEL
gru-0.0.1.dist-info/entry_points.txt
gru-0.0.1.dist-info/top_level.txt
gru-0.0.1.dist-info/RECORD
