Metadata-Version: 2.1
Name: gru
Version: 0.0.1
Summary: Canso Platform's Python package for Data & Machine Learning Usecases
Author-email: Canso Platform Development Team <platform-engineers@yugen.ai>
License: MIT LICENSE
Project-URL: homepage, https://yugen-ai-gru.readthedocs-hosted.com/en/latest/
Project-URL: documentation, https://yugen-ai-gru.readthedocs-hosted.com/en/latest/
Project-URL: repository, https://github.com/Yugen-ai/gru
Classifier: Programming Language :: Python :: 3.10
Classifier: License :: OSI Approved :: MIT License
Classifier: Operating System :: OS Independent
Requires-Python: >=3.7
License-File: LICENSE
Requires-Dist: requests >=2.31.0
Requires-Dist: typing ==3.7.4.3
Requires-Dist: chardet ==5.1.0
Requires-Dist: click >=8.1.7
